jsonmaestro/__init__.py
jsonmaestro/__init__.pyi
jsonmaestro/_logger.py
jsonmaestro/_logger.pyi
jsonmaestro/_logger39.py
jsonmaestro/_logger39.pyi
jsonmaestro/constants.pyi
jsonmaestro/contantants.py
jsonmaestro/converter.py
jsonmaestro/converter.pyi
jsonmaestro/helpers.py
jsonmaestro/helpers.pyi
jsonmaestro/jsonmaestro.py
jsonmaestro/jsonmaestro.pyi
jsonmaestro/loader.py
jsonmaestro/loader.pyi
jsonmaestro/logger.py
jsonmaestro/logger.pyi
jsonmaestro/apps/cli.py
jsonmaestro/apps/converter.py
jsonmaestro-0.0.3.1.dist-info/LICENSE
jsonmaestro-0.0.3.1.dist-info/METADATA
jsonmaestro-0.0.3.1.dist-info/WHEEL
jsonmaestro-0.0.3.1.dist-info/entry_points.txt
jsonmaestro-0.0.3.1.dist-info/top_level.txt
jsonmaestro-0.0.3.1.dist-info/RECORD
