Metadata-Version: 2.1
Name: jsonmaestro
Version: 0.0.3.1
Summary: JSONMaestro is a powerful Python tool designed to clean, process, and optimize JSON-like files.
Author-email: Greg Bowne <gbowne144@gmail.com>
Project-URL: Homepage, https://github.com/gbowne1/json-maestro
Project-URL: Issues, https://github.com/gbowne1/json-maestro/issues
Classifier: Programming Language :: Python :: 3
Classifier: License :: OSI Approved :: MIT License
Classifier: Operating System :: OS Independent
Requires-Python: >=3.9
License-File: LICENSE
Requires-Dist: click
